nothingness/__init__.py
nothingness/__main__.py
nothingness-1.0.0.dist-info/LICENSE
nothingness-1.0.0.dist-info/METADATA
nothingness-1.0.0.dist-info/WHEEL
nothingness-1.0.0.dist-info/entry_points.txt
nothingness-1.0.0.dist-info/top_level.txt
nothingness-1.0.0.dist-info/RECORD
